smm_vk/__init__.py
smm_vk/cli/__init__.py
smm_vk/cli/default.py
smm_vk/cli/groups.py
smm_vk/cli/main.py
smm_vk/cli/object.py
smm_vk/clients/__init__.py
smm_vk/clients/vk_client/__init__.py
smm_vk/clients/vk_client/driver.py
smm_vk/clients/vk_client/models/__init__.py
smm_vk/clients/vk_client/models/groups.py
smm_vk/clients/vk_client/models/utils.py
smm_vk/clients/vk_client/vk_client.py
smm_vk/configs/__init__.py
smm_vk/configs/base.py
smm_vk/configs/vk_auth.py
smm_vk/containers/__init__.py
smm_vk/containers/application.py
smm_vk/containers/vk_client.py
smm_vk/utils/__init__.py
smm_vk/utils/base_file_saver.py
smm_vk/utils/ids_file_saver.py
smm_vk/utils/singleton.py
smm_vk-0.1.0.dist-info/METADATA
smm_vk-0.1.0.dist-info/WHEEL
smm_vk-0.1.0.dist-info/entry_points.txt
smm_vk-0.1.0.dist-info/RECORD
