Metadata-Version: 2.1
Name: smm-vk
Version: 0.1.0
Summary: 
Author: burn_in_soul
Author-email: burn-in-soul@uandex.ru
Requires-Python: >=3.11,<4.0
Classifier: Programming Language :: Python :: 3
Classifier: Programming Language :: Python :: 3.11
Classifier: Programming Language :: Python :: 3.12
Requires-Dist: aiofiles (>=24.1.0,<25.0.0)
Requires-Dist: aiovk (>=4.1.0,<5.0.0)
Requires-Dist: anyio (>=4.4.0,<5.0.0)
Requires-Dist: asyncclick (>=8.1.7.2,<9.0.0.0)
Requires-Dist: httpx (>=0.27.2,<0.28.0)
Requires-Dist: pydantic (>=2.9.1,<3.0.0)
Requires-Dist: pydantic-settings (>=2.5.2,<3.0.0)
Requires-Dist: vk-api (>=11.9.9,<12.0.0)
